report_generator/__init__.py
report_generator/html_tools.py
report_generator/report.py
report_generator/smtp.py
report_generator-0.1.10.dist-info/METADATA
report_generator-0.1.10.dist-info/WHEEL
report_generator-0.1.10.dist-info/top_level.txt
report_generator-0.1.10.dist-info/RECORD
